LICENSE
odd_airflow2_integration/dir/airflow_odd_integrator.py
odd_airflow2_integration/dir/listener.py
odd_airflow2_integration/plugin.py
odd_airflow2_integration-0.0.8.dist-info/WHEEL
odd_airflow2_integration-0.0.8.dist-info/LICENSE
odd_airflow2_integration-0.0.8.dist-info/entry_points.txt
odd_airflow2_integration-0.0.8.dist-info/METADATA
odd_airflow2_integration-0.0.8.dist-info/RECORD
