Metadata-Version: 2.1
Name: odd-airflow2-integration
Version: 0.0.8
Summary: ODD integration with Airflow
Home-page: https://github.com/opendatadiscovery/odd-airflow-2
License: Apache-2.0
Keywords: airflow2,opendatadiscovery
Author: Open Data Discovery
Author-email: pypi@opendatadiscovery.org
Requires-Python: >=3.9,<4.0
Classifier: License :: OSI Approved :: Apache Software License
Classifier: Programming Language :: Python :: 3
Classifier: Programming Language :: Python :: 3.9
Classifier: Programming Language :: Python :: 3.10
Classifier: Programming Language :: Python :: 3.11
Requires-Dist: odd-models (>=2.0.12,<3.0.0)
Project-URL: Repository, https://github.com/opendatadiscovery/odd-airflow-2
